setup.py
magma/__future__.py
magma/__init__.py
magma/create_phex_release_magmas.py
magma/create_simple_magma_list.py
magma/magma_creator_cli.py
magma/magma_creator_cli_proof_of_concept.py
magma/magma_list.py
magma/make_phex_release_magmas.py
magma/sha1_gnutella.py
magma.egg-info/PKG-INFO
magma.egg-info/SOURCES.txt
magma.egg-info/dependency_links.txt
magma.egg-info/requires.txt
magma.egg-info/top_level.txt