Metadata-Version: 1.0
Name: magma
Version: 0.3.9
Summary: MAGnet MAnifest Management - Readout and create lists of magnets in yaml format. 
Home-page: http://freehg.org/u/ArneBab/magma
Author: Arne Babenhauserheide
Author-email: arne_bab@web.de
License: GNU GPL-3 or later
Keywords: magma,yaml,p2p,magnet,gnutella
Platform: any
Classifier: License :: OSI Approved :: GNU General Public License (GPL)
Classifier: Programming Language :: Python
Classifier: Operating System :: OS Independent
Classifier: Topic :: Software Development :: Libraries :: Python Modules
Classifier: Topic :: Communications :: File Sharing
Classifier: Topic :: Communications :: File Sharing :: Gnutella
Classifier: Intended Audience :: Developers
Classifier: Intended Audience :: End Users/Desktop
Classifier: Environment :: Console
Classifier: Development Status :: 1 - Planning
